Workbook

Sheet Matriz Ckeck LIst
C3: MATRIZ PARA COMPROBACIÓN REQUERIMIENTOS DE CALIDAD DE PROYECTO ACADEMICO
D5: SISTEMA: | E5: SISTEMA DE GESTION DE CRIANZA DE CONEJOS (Hoptolt)
F6: Requerimientos Funcionales
B7: Nº | C7: CRITERIOS DE CALIDAD (Documento/Requerimientos) | E7: Status Nivel de Acuerdo | F7: RF - 002 Ingresar Información | G7: Status Nivel de Acuerdo | H7: 100 | I7: RF - 004 Generar reporte de pagos | J7: Status Nivel de Acuerdo | K7: RF - 006 Eliminar Información
H8: 0
B9: 1 | C9: Agreed | E9: NOK | F9: En este caso, y con las herramientas disponibles no se puede asegurar que el requisito haya sido acordado y que todos los interesados están de acuerdo con este requisito. | G9: NOK | H9: En este caso, y con las herramientas disponibles no se puede asegurar que el requisito haya sido acordado y que todos los interesados están de acuerdo con este requisito. | I9: En este caso, y con las herramientas disponibles no se puede asegurar que el requisito haya sido acordado y que todos los interesados están de acuerdo con este requisito. | J9: NOK | K9: En este caso, y con las herramientas disponibles no se puede asegurar que el requisito haya sido acordado y que todos los interesados están de acuerdo con este requisito.
B10: 2 | C10: Ranked | E10: OK | F10: El requisito se pondera por importancia, teniendo filas como "Importacia" o "Urgencia" lo que demuestra que si esta clasificado por importancia | G10: OK | I10: El requisito se pondera por importancia, teniendo filas como "Importacia" o "Urgencia" lo que demuestra que si esta clasificado por importancia | J10: OK | K10: El requisito se pondera por importancia, teniendo filas como "Importacia" o "Urgencia" lo que demuestra que si esta clasificado por importancia
B11: 3 | C11: Unambiguos | E11: NOK | F11: No se puede entender bien a lo que se refiere con cambiar los parámetros, que parámetros se puede, se puede eliminar el parámetro anterior. Además mezcla con otro caso de uso, que es el "Registro de Pagos" | G11: OK | I11: Se comprende de manera clara a lo que tiene que referirse con el caso de uso de generar reporte de pagos, la información, no tiene ambiguedades ni dobles interpretaciones | J11: OK | K11: Se comprende de manera clara a lo que tiene que referirse con el caso de uso de eliminar información, no tiene ambiguedades ni dobles interpretaciones
B12: 4 | C12: Valid and up-to date | E12: OK | F12: La información con respecta al ingreso de información se ha incorporaoa correctamente. | G12: OK | I12: La información con respecta a generar reportes de pago ha sido incorporada correctamente, se tiene que debe de ir en la tabla y la extensión del archivo que se va a generar | J12: OK | K12: La información correspondiente ha sido añadida teniendo en cuenta el flujo normal y lo que debe de tener este caso de uso.
B13: 5 | C13: Correct | E13: OK | F13: Las expectativas del usuario se ven reflejadas correctamente al mostrar lo que se desea hacer al momento de agregar información con los atributos correspondientes a este | G13: OK | I13: Las expectativas del usuario se ven reflejadas correctamente al mostrar lo que se desea generar con que parametros se puede generare | J13: NOK | K13: Las expectativas del usuario no se ven completamente reflejadas, además tiene términos no adecuados hacia el usuario como "BD"
B14: 6 | C14: Consisten | E14: OK | F14: No tiene contradicciones, se refleja calramente que se quiere hacer al momento de ingresar información | G14: OK | I14: No tiene contradicciones, se refleja calramente que se quiere generar con la información que se expone en el requisito | J14: OK | K14: No tiene contradicciones, se refleja calramente que se quiere eliminar información asociada a un usuario y esto es consistente a lo largo del requisito funcional
B15: 7 | C15: Verifiable | E15: NOK | F15: No se puede verificar si este requisito fue implementado ni mucho menos con un esfuerzo razonable, entonces no cumple | G15: NOK | I15: No se puede verificar si este requisito fue implementado ni mucho menos con un esfuerzo razonable, entonces no cumple | J15: NOK | K15: No se puede verificar si este requisito fue implementado ni mucho menos con un esfuerzo razonable, entonces no cumple
B16: 8 | C16: Realizable | E16: NOK | F16: No puede ser implementado ya que no se demuestra una matriz de costos o de tiempo por lo cual no se puede saber si es que puede o no puede ser implementado | G16: NOK | I16: No puede ser implementado ya que no se demuestra una matriz de costos o de tiempo por lo cual no se puede saber si es que puede o no puede ser implementado | J16: NOK | K16: No puede ser implementado ya que no se demuestra una matriz de costos o de tiempo por lo cual no se puede saber si es que puede o no puede ser implementado
B17: 9 | C17: Traceable | E17: OK | F17: Los requisitos, en la pagina 35 del documento, demuestran los requisitos funcionales y los no funcionales que estan asociados a los diferentes objetivos, ademas puede visualizar si es que se cambia un requisito, afecta a los demás | G17: OK | I17: Los requisitos, en la pagina 35 del documento, demuestran los requisitos funcionales y los no funcionales que estan asociados a los diferentes objetivos, ademas puede visualizar si es que se cambia un requisito, afecta a los demás | J17: OK | K17: Los requisitos, en la pagina 35 del documento, demuestran los requisitos funcionales y los no funcionales que estan asociados a los diferentes objetivos, ademas puede visualizar si es que se cambia un requisito, afecta a los demás
B18: 10 | C18: Complete | E18: OK | F18: Trata los asuntos relevantes con respecto al requisito funcional, lo que quiere decir este requisito y además el flujo normal y excepcional que puede tener | G18: OK | I18: Trata los asuntos relevantes con respecto al requisito funcional, lo que quiere decir este requisito y además el flujo normal y excepcional que puede tener | J18: OK | K18: Trata los asuntos relevantes con respecto al requisito funcional, lo que quiere decir este requisito y además el flujo normal y excepcional que puede tener
B19: 11 | C19: Understandability | E19: OK | F19: Los interesados pueden estar involucrados en todo el tiempo con respecto a este requisito funcional | G19: OK | I19: Los interesados pueden estar involucrados en todo el tiempo con respecto a este requisito funcional | J19: OK | K19: Los interesados pueden estar involucrados en todo el tiempo con respecto a este requisito funcional

Sheet M LISTA DE COMPROBACIO RF002
B1: SISTEMA:
B2: FECHA: | C2: 45967
B3: AUTOR: | C3: Jhordy Marcillo
B4: REQUERIMIENTOS EVALUADOS : | C4: RF - 002 Ingresar Información
A6: CONTENIDO
A7: No. | B7: Pregunta | C7: SI | D7: NO
A8: 1 | B8: Todos los requerimientos relevantes se han documentado? | C8: x
A9: 2 | B9: Se han implementado las funciones requeridas? | D9: x
A10: 3 | B10: Existe algún mecanismo que permita seguir el impacto de dicho requerimiento a lo largo del resto de las actividades del ciclo productivo.? | C10: x
A11: 4 | B11: El origen de cada requerimento individual está claro ? | C11: x
A12: 5 | B12: Que tan facil es devolverse a los requerimientos? | C12: x
A13: 6 | B13: Los requerimientos reflejan las necesidades y deseos del cliente? | C13: x
A14: 7 | B14: No hay contradicciones entre los requerimientos? | C14: x
A15: 8 | B15: El requerimiento que se esta especificando contribuye a alcanzar un objetivo definido ? | C15: x
A16: 9 | B16: Existe un proceso acotado (en plazo y presupuesto) que permita determinar que el sistema construido satisface lo descrito en el propio requerimiento? | D16: x
A17: SUMATORIA: | C17: =COUNTA('M LISTA DE COMPROBACIO RF002'!$C$8:$C$16) -> 7 | D17: =COUNTA('M LISTA DE COMPROBACIO RF002'!$D$8:$D$16) -> 2
A18: PORCENTAJE : | C18: =C17/9 -> 0.77777778 | D18: =D17/9 -> 0.22222222
A20: DOCUMENTACIÓN
A21: No. | B21: Pregunta | C21: SI | D21: NO
A22: 1 | B22: Aplica un estandar para la documetación de requerimiento? | C22: x
A23: 2 | B23: Cumple con la estructura definida por el estandar? | C23: x
A24: 3 | B24: Utiliza un Glosario de términos normalizado? | D24: x
A25: 4 | B25: Los requerimientos Funcionales estan sujetos a una única interpretación? | C25: x
A26: 5 | B26: El modelo aplicado cumple con la sintaxis? | C26: x
A27: SUMATORIA: | C27: =COUNTA('M LISTA DE COMPROBACIO RF002'!$C$22:$C$26) -> 4 | D27: =COUNTA('M LISTA DE COMPROBACIO RF002'!$D$22:$D$26) -> 1
A28: PORCENTAJE : | C28: =C27/5 -> 0.8 | D28: =D27/5 -> 0.2
A30: NIVEL DE ACUERDO
A31: No. | B31: Pregunta | C31: SI | D31: NO
A32: 1 | B32: Todos los requerimientos han sido acordados con todos los interesados? | D32: x
A33: 2 | B33: Todos los requerimientos modificados han sido acordados por todos los implicados? | D33: x
A34: 3 | B34: Han sido resueltos todos los conflictos conocidos respectos de los requerimientos? | C34: x
A35: SUMATORIA: | C35: =COUNTA('M LISTA DE COMPROBACIO RF002'!$C$32:$C$34) -> 1 | D35: =COUNTA('M LISTA DE COMPROBACIO RF002'!$D$32:$D$34) -> 2
A36: PORCENTAJE : | C36: =C35/3 -> 0.33333333 | D36: =D35/3 -> 0.66666667
A40: RESUMEN
B41: CONTENIDO
B42: DOCUMENTACIÓN
B43: NIVEL DE ACUERDO

Sheet M LISTA DE COMPROBACIO RF004
B1: SISTEMA:
B2: FECHA: | C2: 45967
B3: AUTOR: | C3: Jhordy Marcillo
B4: REQUERIMIENTOS EVALUADOS : | C4: RF - 004 Generar reportes
A6: CONTENIDO
A7: No. | B7: Pregunta | C7: SI | D7: NO
A8: 1 | B8: Todos los requerimientos relevantes se han documentado? | C8: x
A9: 2 | B9: Se han implementado las funciones requeridas? | D9: x
A10: 3 | B10: Existe algún mecanismo que permita seguir el impacto de dicho requerimiento a lo largo del resto de las actividades del ciclo productivo.? | C10: x
A11: 4 | B11: El origen de cada requerimento individual está claro ? | C11: x
A12: 5 | B12: Que tan facil es devolverse a los requerimientos? | C12: x
A13: 6 | B13: Los requerimientos reflejan las necesidades y deseos del cliente? | C13: x
A14: 7 | B14: No hay contradicciones entre los requerimientos? | C14: x
A15: 8 | B15: El requerimiento que se esta especificando contribuye a alcanzar un objetivo definido ? | C15: x
A16: 9 | B16: Existe un proceso acotado (en plazo y presupuesto) que permita determinar que el sistema construido satisface lo descrito en el propio requerimiento? | D16: x
A17: SUMATORIA: | C17: =COUNTA('M LISTA DE COMPROBACIO RF004'!$C$8:$C$16) -> 7 | D17: =COUNTA('M LISTA DE COMPROBACIO RF004'!$D$8:$D$16) -> 2
A18: PORCENTAJE : | C18: =C17/9 -> 0.77777778 | D18: =D17/9 -> 0.22222222
A20: DOCUMENTACIÓN
A21: No. | B21: Pregunta | C21: SI | D21: NO
A22: 1 | B22: Aplica un estandar para la documetación de requerimiento? | C22: x
A23: 2 | B23: Cumple con la estructura definida por el estandar? | C23: x
A24: 3 | B24: Utiliza un Glosario de términos normalizado? | D24: x
A25: 4 | B25: Los requerimientos Funcionales estan sujetos a una única interpretación? | C25: x
A26: 5 | B26: El modelo aplicado cumple con la sintaxis? | C26: x
A27: SUMATORIA: | C27: =COUNTA('M LISTA DE COMPROBACIO RF004'!$C$22:$C$26) -> 4 | D27: =COUNTA('M LISTA DE COMPROBACIO RF004'!$D$22:$D$26) -> 1
A28: PORCENTAJE : | C28: =C27/5 -> 0.8 | D28: =D27/5 -> 0.2
A30: NIVEL DE ACUERDO
A31: No. | B31: Pregunta | C31: SI | D31: NO
A32: 1 | B32: Todos los requerimientos han sido acordados con todos los interesados? | D32: x
A33: 2 | B33: Todos los requerimientos modificados han sido acordados por todos los implicados? | D33: x
A34: 3 | B34: Han sido resueltos todos los conflictos conocidos respectos de los requerimientos? | C34: x
A35: SUMATORIA: | C35: =COUNTA('M LISTA DE COMPROBACIO RF004'!$C$32:$C$34) -> 1 | D35: =COUNTA('M LISTA DE COMPROBACIO RF004'!$D$32:$D$34) -> 2
A36: PORCENTAJE : | C36: =C35/3 -> 0.33333333 | D36: =D35/3 -> 0.66666667
A40: RESUMEN
B41: CONTENIDO
B42: DOCUMENTACIÓN
B43: NIVEL DE ACUERDO

Sheet M LISTA DE COMPROBACIO RF006
B1: SISTEMA:
B2: FECHA: | C2: 45967
B3: AUTOR: | C3: Jhordy Marcillo
B4: REQUERIMIENTOS EVALUADOS : | C4: RF - 006 Eliminar Informacion
A6: CONTENIDO
A7: No. | B7: Pregunta | C7: SI | D7: NO
A8: 1 | B8: Todos los requerimientos relevantes se han documentado? | C8: x
A9: 2 | B9: Se han implementado las funciones requeridas? | D9: x
A10: 3 | B10: Existe algún mecanismo que permita seguir el impacto de dicho requerimiento a lo largo del resto de las actividades del ciclo productivo.? | C10: x
A11: 4 | B11: El origen de cada requerimento individual está claro ? | C11: x
A12: 5 | B12: Que tan facil es devolverse a los requerimientos? | C12: x
A13: 6 | B13: Los requerimientos reflejan las necesidades y deseos del cliente? | C13: x
A14: 7 | B14: No hay contradicciones entre los requerimientos? | C14: x
A15: 8 | B15: El requerimiento que se esta especificando contribuye a alcanzar un objetivo definido ? | C15: x
A16: 9 | B16: Existe un proceso acotado (en plazo y presupuesto) que permita determinar que el sistema construido satisface lo descrito en el propio requerimiento? | D16: x
A17: SUMATORIA: | C17: =COUNTA('M LISTA DE COMPROBACIO RF006'!$C$8:$C$16) -> 7 | D17: =COUNTA('M LISTA DE COMPROBACIO RF006'!$D$8:$D$16) -> 2
A18: PORCENTAJE : | C18: =C17/9 -> 0.77777778 | D18: =D17/9 -> 0.22222222
A20: DOCUMENTACIÓN
A21: No. | B21: Pregunta | C21: SI | D21: NO
A22: 1 | B22: Aplica un estandar para la documetación de requerimiento? | C22: x
A23: 2 | B23: Cumple con la estructura definida por el estandar? | C23: x
A24: 3 | B24: Utiliza un Glosario de términos normalizado? | D24: x
A25: 4 | B25: Los requerimientos Funcionales estan sujetos a una única interpretación? | C25: x
A26: 5 | B26: El modelo aplicado cumple con la sintaxis? | C26: x
A27: SUMATORIA: | C27: =COUNTA('M LISTA DE COMPROBACIO RF006'!$C$22:$C$26) -> 4 | D27: =COUNTA('M LISTA DE COMPROBACIO RF006'!$D$22:$D$26) -> 1
A28: PORCENTAJE : | C28: =C27/5 -> 0.8 | D28: =D27/5 -> 0.2
A30: NIVEL DE ACUERDO
A31: No. | B31: Pregunta | C31: SI | D31: NO
A32: 1 | B32: Todos los requerimientos han sido acordados con todos los interesados? | D32: x
A33: 2 | B33: Todos los requerimientos modificados han sido acordados por todos los implicados? | D33: x
A34: 3 | B34: Han sido resueltos todos los conflictos conocidos respectos de los requerimientos? | C34: x
A35: SUMATORIA: | C35: =COUNTA('M LISTA DE COMPROBACIO RF006'!$C$32:$C$34) -> 1 | D35: =COUNTA('M LISTA DE COMPROBACIO RF006'!$D$32:$D$34) -> 2
A36: PORCENTAJE : | C36: =C35/3 -> 0.33333333 | D36: =D35/3 -> 0.66666667
A40: RESUMEN
B41: CONTENIDO
B42: DOCUMENTACIÓN
B43: NIVEL DE ACUERDO

Sheet RECOMENDACIONES - RF - 002
A1: PREGUNTA | B1: RECOMENDACIÓN
A2: ¿Se han validado y aprobado formalmente todos los entregables de la entrevista (videoconferencia, minuta, acta de aceptación)? | B2: Establecer firmas digitales o un acta de reunión oficial tras cada sesión de descubrimiento, de modo que quede constancia inequívoca de la aprobación de alcance y contenido por parte de tutor, cliente y equipo.
A3: ¿El requisito tiene una sola interpretación no importando quien lo lea? | B3: Poner solamente un requisito en la descripción ya que en este requisito ponen otro posible requisito, el "Registro de Pagos", lo cual sería mejor poner separados para una mejor interpretación
A4: ¿Se puede verificar que este requisito es verificable demostrando su esfuerzo razonable? | B4: Reflejar los esfuerzos del equipo y de los interesados para hacer que este requisito se pueda verificar con todos los interesados y también con los integrantes del equipo
A5: ¿El requisito demuestra que puede ser identificado y completado en las condiciones actuales en las que se encuentra? | B5: Explicar o demostrar que este requisito funcional puede ser completado demostrando una matriz de costos, o de tiempo que tomaría implementar por completo este requisito

Sheet RECOMENDACIONES - RF - 004
A1: PREGUNTA | B1: RECOMENDACIÓN
A2: ¿Se han validado y aprobado formalmente todos los entregables de la entrevista (videoconferencia, minuta, acta de aceptación)? | B2: Establecer firmas digitales o un acta de reunión oficial tras cada sesión de descubrimiento, de modo que quede constancia inequívoca de la aprobación de alcance y contenido por parte de tutor, cliente y equipo.
A3: ¿Se puede verificar que este requisito es verificable demostrando su esfuerzo razonable? | B3: Reflejar los esfuerzos del equipo y de los interesados para hacer que este requisito se pueda verificar con todos los interesados y también con los integrantes del equipo
A4: ¿El requisito demuestra que puede ser identificado y completado en las condiciones actuales en las que se encuentra? | B4: Explicar o demostrar que este requisito funcional puede ser completado demostrando una matriz de costos, o de tiempo que tomaría implementar por completo este requisito

Sheet RECOMENDACIONES - RF - 006
A1: PREGUNTA | B1: RECOMENDACIÓN
A2: ¿Se han validado y aprobado formalmente todos los entregables de la entrevista (videoconferencia, minuta, acta de aceptación)? | B2: Establecer firmas digitales o un acta de reunión oficial tras cada sesión de descubrimiento, de modo que quede constancia inequívoca de la aprobación de alcance y contenido por parte de tutor, cliente y equipo.
A3: ¿Se han definido y concretado todas las expectativas de los involucrados? | B3: Reflejar las expectativas del usuario, que es lo que desea y a donde va orientado el deseo con respecto a este requisito del usuario en cuestion
A4: ¿Se puede verificar que este requisito es verificable demostrando su esfuerzo razonable? | B4: Reflejar los esfuerzos del equipo y de los interesados para hacer que este requisito se pueda verificar con todos los interesados y también con los integrantes del equipo
A5: ¿El requisito demuestra que puede ser identificado y completado en las condiciones actuales en las que se encuentra? | B5: Explicar o demostrar que este requisito funcional puede ser completado demostrando una matriz de costos, o de tiempo que tomaría implementar por completo este requisito
